outlier_analysis.py
outlier_analysis-1.0.0.dist-info/LICENSE
outlier_analysis-1.0.0.dist-info/METADATA
outlier_analysis-1.0.0.dist-info/WHEEL
outlier_analysis-1.0.0.dist-info/top_level.txt
outlier_analysis-1.0.0.dist-info/RECORD
