Metadata-Version: 2.1
Name: outlier-analysis
Version: 1.0.0
Summary: Automatically detect, remove, and retrieve outliers using Standard Deviation, DBSCAN and Local Outlier Factor
Home-page: https://github.com/cmbfuqua/outlier_detection_drl
Author: Ben Fuqua
Author-email: Benjamin.Fuqua@gmail.com
License: UNKNOWN
Platform: UNKNOWN
Classifier: Development Status :: 4 - Beta
Classifier: Intended Audience :: Other Audience
Classifier: License :: OSI Approved :: MIT License
Classifier: Natural Language :: English
Classifier: Operating System :: OS Independent
Classifier: Programming Language :: Python :: 3 :: Only
Classifier: Programming Language :: Python :: 3.8
Classifier: Programming Language :: Python :: 3.9
Requires-Dist: pandas (~=1.2.4)
Requires-Dist: numpy (~=1.19.5)
Requires-Dist: sklearn (~=0.0)
Requires-Dist: joblib (~=1.0.1)
